nvat/__init__.py
nvat/helper.py
nvat/main.py
nvat/template/buildVars.py
nvat/template/manifest-translated.ini.tpl
nvat/template/manifest.ini.tpl
nvat/template/pyproject.toml
nvat/template/pyrightconfig.json
nvat/template/sconstruct
nvat/template/addon/globalPlugins/$name/__init__.py
nvat/template/site_scons/site_tools/gettexttool/__init__.py
nvat-1.0.1.dist-info/METADATA
nvat-1.0.1.dist-info/WHEEL
nvat-1.0.1.dist-info/entry_points.txt
nvat-1.0.1.dist-info/top_level.txt
nvat-1.0.1.dist-info/RECORD
