Metadata-Version: 2.4
Name: nvat
Version: 1.0.1
Summary: An NVDA addon creator tool
Author-email: Ashu Choudhury <ashu@ashuchoudhury.in>
Requires-Python: >=3.8
Requires-Dist: requests
